email_service_toolkit/__init__.py
email_service_toolkit/email_service.py
email_service_toolkit/template_service.py
email_service_toolkit-0.1.6.dist-info/METADATA
email_service_toolkit-0.1.6.dist-info/WHEEL
email_service_toolkit-0.1.6.dist-info/top_level.txt
email_service_toolkit-0.1.6.dist-info/RECORD
