Metadata-Version: 2.4
Name: email_service_toolkit
Version: 0.1.6
Summary: Reusable Python toolkit for sending emails and managing email templates
Home-page: https://github.com/vamsichowdaryg/email_service_toolkit
Author: Vamsi Gudapati
Author-email: vamsi7673916775@gmail.com
License: MIT
Classifier: Programming Language :: Python :: 3
Classifier: License :: OSI Approved :: MIT License
Classifier: Operating System :: OS Independent
Classifier: Topic :: Software Development :: Libraries :: Python Modules
Classifier: Intended Audience :: Developers
Requires-Python: >=3.8
Requires-Dist: aiohttp>=3.8.0
Requires-Dist: fastapi>=0.102.0
Requires-Dist: python-dotenv>=1.0.0
Dynamic: author
Dynamic: author-email
Dynamic: classifier
Dynamic: description-content-type
Dynamic: home-page
Dynamic: license
Dynamic: requires-dist
Dynamic: requires-python
Dynamic: summary
